easypush/__init__.py
easypush/admin.py
easypush/apps.py
easypush/forms.py
easypush/models.py
easypush/serializers.py
easypush/tests.py
easypush/urls.py
easypush/views.py
easypush/backends/__init__.py
easypush/backends/base/__init__.py
easypush/backends/base/base.py
easypush/backends/base/body.py
easypush/backends/ding_talk/__init__.py
easypush/backends/ding_talk/client.py
easypush/backends/ding_talk/parser.py
easypush/backends/email/__init__.py
easypush/backends/feishu/__init__.py
easypush/backends/feishu/client.py
easypush/backends/feishu/message.py
easypush/backends/feishu/parser.py
easypush/backends/feishu/api/__init__.py
easypush/backends/feishu/api/body.py
easypush/backends/feishu/api/token.py
easypush/backends/qy_weixin/__init__.py
easypush/backends/qy_weixin/client.py
easypush/backends/qy_weixin/message.py
easypush/backends/qy_weixin/parser.py
easypush/backends/qy_weixin/api/__init__.py
easypush/backends/qy_weixin/api/body.py
easypush/backends/sms/__init__.py
easypush/client/__init__.py
easypush/client/loader.py
easypush/client/message.py
easypush/client/utils.py
easypush/core/__init__.py
easypush/core/crypto.py
easypush/core/globals.py
easypush/core/path_builder.py
easypush/core/db/__init__.py
easypush/core/db/base.py
easypush/core/locker/__init__.py
easypush/core/locker/lock.py
easypush/core/locker/watch.py
easypush/core/mq/__init__.py
easypush/core/mq/autodiscover.py
easypush/core/mq/context.py
easypush/core/request/__init__.py
easypush/core/request/http_client.py
easypush/core/request/multipart.py
easypush/migrations/0001_initial.py
easypush/migrations/0002_remove_appmessagemodel_media_and_more.py
easypush/migrations/0003_alter_appmsgpushrecordmodel_msg_uid_and_more.py
easypush/migrations/0004_appmediastoragemodel_expire_time.py
easypush/migrations/0005_alter_appmediastoragemodel_expire_time_and_more.py
easypush/migrations/0006_alter_appmsgpushrecordmodel_table.py
easypush/migrations/0007_alter_apptokenplatformmodel_agent_id_and_more.py
django_easypush-1.1.3.dist-info/LICENSE
django_easypush-1.1.3.dist-info/METADATA
django_easypush-1.1.3.dist-info/WHEEL
django_easypush-1.1.3.dist-info/top_level.txt
django_easypush-1.1.3.dist-info/RECORD
