Metadata-Version: 2.1
Name: django-easypush
Version: 1.1.3
Summary: 集成钉钉、企业微信的企业内部应用消息推送系统（支持MQ异步推送）
Home-page: https://github.com/luojidr/django-easypush
Author: luojidr
Author-email: luojidr@163.com
Maintainer: luojidr
Maintainer-email: luojidr@163.com
License: MIT
Classifier: Programming Language :: Python :: 3.8
Classifier: Programming Language :: Python :: 3.9
Classifier: Programming Language :: Python :: 3.10
Classifier: Programming Language :: Python :: 3.11
Classifier: License :: OSI Approved :: MIT License
Classifier: Operating System :: OS Independent
Classifier: Framework :: Django
Classifier: Framework :: Django :: 3.2
Classifier: Framework :: Django :: 4.0
Classifier: Intended Audience :: Developers
Requires-Python: >=3.8
License-File: LICENSE
Requires-Dist: django (<=4.1.3,>=3.1.14)
Requires-Dist: django-extensions (>=3.0.9)
Requires-Dist: djangorestframework (>=3.12.1)
Requires-Dist: django-redis (>=4.11.0)
Requires-Dist: werkzeug (>=1.0.1)
Requires-Dist: dingtalk-sdk (==1.3.8)
Requires-Dist: bson (==0.5.10)
Requires-Dist: loguru (>=0.6.0)
Requires-Dist: python-dotenv (>=0.21.0)
Requires-Dist: pyyaml (>=6.0)
Requires-Dist: mysqlclient (>=2.0.2)
Requires-Dist: pycryptodome (>=3.9.8)
Requires-Dist: celery (<6.0,>=5.0.0)
Requires-Dist: django-celery-results (>=2.3.1)
Requires-Dist: django-celery-beat (>=2.4.0)
Requires-Dist: gevent (>=20.12.0)
